example_package_samreynoldsmath/__init__.py
example_package_samreynoldsmath/jacobi.py
example_package_samreynoldsmath/solver.py
example_package_samreynoldsmath-0.2.1.dist-info/LICENSE
example_package_samreynoldsmath-0.2.1.dist-info/METADATA
example_package_samreynoldsmath-0.2.1.dist-info/WHEEL
example_package_samreynoldsmath-0.2.1.dist-info/RECORD
