Metadata-Version: 2.1
Name: example_package_samreynoldsmath
Version: 0.2.1
Summary: A simple demo of how to structure, use, and publish a Python package.
License: MIT
Author: Sam Reynolds
Author-email: sreyn@proton.me
Requires-Python: >=3.11,<4.0
Classifier: License :: OSI Approved :: MIT License
Classifier: Programming Language :: Python :: 3
Classifier: Programming Language :: Python :: 3.11
Classifier: Programming Language :: Python :: 3.12
Requires-Dist: numpy (>=1.26.4,<2.0.0)
